scsampler/__init__.py
scsampler/main.py
scsampler/uclab.py
scsampler_dongyuan-0.0.1.dist-info/LICENCE
scsampler_dongyuan-0.0.1.dist-info/METADATA
scsampler_dongyuan-0.0.1.dist-info/WHEEL
scsampler_dongyuan-0.0.1.dist-info/top_level.txt
scsampler_dongyuan-0.0.1.dist-info/RECORD
